markdown_vimwiki/__init__.py
markdown_vimwiki/extension.py
markdown_vimwiki-0.1.2.dist-info/LICENSE
markdown_vimwiki-0.1.2.dist-info/METADATA
markdown_vimwiki-0.1.2.dist-info/WHEEL
markdown_vimwiki-0.1.2.dist-info/top_level.txt
markdown_vimwiki-0.1.2.dist-info/RECORD
