Metadata-Version: 2.1
Name: markdown-vimwiki
Version: 0.1.2
Summary: Markdown extension for vimwiki todos and tags
Home-page: https://github.com/makyo/markdown-vimwiki
Author: Madison Scott-Clary
Author-email: makyo@drab-makyo.com
License: UNKNOWN
Platform: UNKNOWN
Classifier: Development Status :: 4 - Beta
Classifier: License :: OSI Approved :: MIT License
Classifier: Operating System :: OS Independent
Classifier: Topic :: Text Processing
Classifier: Programming Language :: Python :: 3
Requires-Dist: markdown
